cpntools4py/__init__.py
cpntools4py/petri_net/__init__.py
cpntools4py/petri_net/net.py
cpntools4py/petri_net/utils.py
cpntools4py/petri_net/obj/__init__.py
cpntools4py/petri_net/obj/arc.py
cpntools4py/petri_net/obj/place.py
cpntools4py/petri_net/obj/transition.py
cpntools4py-1.2.2.dist-info/METADATA
cpntools4py-1.2.2.dist-info/WHEEL
cpntools4py-1.2.2.dist-info/top_level.txt
cpntools4py-1.2.2.dist-info/RECORD
