Metadata-Version: 2.1
Name: cpntools4py
Version: 1.2.2
Summary: Support parsing of xml file which export color petri net from CPNTools
Home-page: https://gitlab.ie.u-ryukyu.ac.jp/k208576/cpntools4py
Author: k208576
Author-email: k208576@ie.u-ryukyu.ac.jp
License: MIT
Platform: UNKNOWN
Classifier: Programming Language :: Python :: 3.9
Classifier: Programming Language :: Python :: 3.8
Classifier: Programming Language :: Python :: 3.7
Classifier: License :: OSI Approved :: MIT License
Requires-Dist: SNAKES
